snakefmt/__init__.py
snakefmt/__main__.py
snakefmt/config.py
snakefmt/diff.py
snakefmt/exceptions.py
snakefmt/formatter.py
snakefmt/logging.py
snakefmt/snakefmt.py
snakefmt/types.py
snakefmt/parser/grammar.py
snakefmt/parser/parser.py
snakefmt/parser/syntax.py
snakefmt-0.11.3.dist-info/METADATA
snakefmt-0.11.3.dist-info/WHEEL
snakefmt-0.11.3.dist-info/entry_points.txt
snakefmt-0.11.3.dist-info/licenses/LICENSE
snakefmt-0.11.3.dist-info/RECORD
