Metadata-Version: 2.4
Name: snakefmt
Version: 0.11.3
Summary: The uncompromising Snakemake code formatter
Project-URL: Homepage, https://github.com/snakemake/snakefmt
Project-URL: Repository, https://github.com/snakemake/snakefmt
Project-URL: Documentation, https://github.com/snakemake/snakefmt/blob/master/README.md
Project-URL: Snakemake Documentation, https://snakemake.readthedocs.io/
Project-URL: Snakemake Repository, https://github.com/snakemake/snakemake
Author-email: Michael Hall <mhaldini@icloud.com>, Brice Letcher <brice.letcher@ens-lyon.fr>
License-Expression: MIT
License-File: LICENSE
Keywords: black,code,formatter,management,parser,python,snakemake,systems,workflow
Requires-Python: <4,>=3.11
Requires-Dist: black<25,>=24.3.0
Requires-Dist: click<9,>=8.2.0
